Metadata-Version: 2.1
Name: hillary-distributions
Version: 0.1
Summary: Gaussian distributions
Home-page: UNKNOWN
License: UNKNOWN
Platform: UNKNOWN
License-File: license.txt
